cc_dida365/__init__.py
cc_dida365/client.py
cc_dida365/endpoints.py
cc_dida365/errors.py
cc_dida365/helpers.py
cc_dida365/typing.py
cc_dida365-0.3.dist-info/METADATA
cc_dida365-0.3.dist-info/WHEEL
cc_dida365-0.3.dist-info/top_level.txt
cc_dida365-0.3.dist-info/RECORD
