Metadata-Version: 2.1
Name: cc-dida365
Version: 0.3
Summary: my dida package
Home-page: https://github.com/houm01/cc-dida365
